bwfilters/__init__.py
bwfilters/py.typed
bwfilters-0.1.0.dist-info/AUTHORS.md
bwfilters-0.1.0.dist-info/LICENSE
bwfilters-0.1.0.dist-info/METADATA
bwfilters-0.1.0.dist-info/WHEEL
bwfilters-0.1.0.dist-info/top_level.txt
bwfilters-0.1.0.dist-info/RECORD
